<?xml version='1.0' encoding='UTF-8'?>
<fingerprint>
  <timestamp>2015-10-21 11:03:04.849 UTC</timestamp>
  <original>
    <name>DEMO-GATLING-GET-BENCHMARKING-RESULTS/com.gatling.demo:gatling-demo-script</name>
    <number>29</number>
  </original>
  <md5sum>87ebe9fe15d84a8b7ff69249d875401d</md5sum>
  <fileName>com.gatling.demo:gatling-demo-script-1.0-SNAPSHOT.jar</fileName>
  <usages>
    <entry>
      <string>DEMO-GATLING-GET-BENCHMARKING-RESULTS/com.gatling.demo:gatling-demo-script</string>
      <ranges>29</ranges>
    </entry>
    <entry>
      <string>DEMO-GATLING-GET-BENCHMARKING-RESULTS</string>
      <ranges>29</ranges>
    </entry>
  </usages>
  <facets/>
</fingerprint>